[
    {
        "key": "dbln",
        "value": "%7B%2261578548880800%22%3A%22SsGYCTAP%22%7D",
        "domain": "facebook.com",
        "path": "/login/device-based/",
        "hostOnly": false,
        "creation": "2026-03-25T22:21:59.825Z",
        "lastAccessed": "2026-03-25T22:21:59.825Z"
    },
    {
        "key": "datr",
        "value": "flzEaSKct6Pkt3qOX5VlJfAX",
        "domain": "facebook.com",
        "path": "/",
        "hostOnly": false,
        "creation": "2026-03-25T22:21:59.825Z",
        "lastAccessed": "2026-03-25T22:21:59.825Z"
    },
    {
        "key": "sb",
        "value": "flzEabp-UtC9gg0wsv_tU9ll",
        "domain": "facebook.com",
        "path": "/",
        "hostOnly": false,
        "creation": "2026-03-25T22:21:59.825Z",
        "lastAccessed": "2026-03-25T22:21:59.825Z"
    },
    {
        "key": "m_pixel_ratio",
        "value": "2.294114351272583",
        "domain": "facebook.com",
        "path": "/",
        "hostOnly": false,
        "creation": "2026-03-25T22:21:59.825Z",
        "lastAccessed": "2026-03-25T22:21:59.825Z"
    },
    {
        "key": "wd",
        "value": "424x942",
        "domain": "facebook.com",
        "path": "/",
        "hostOnly": false,
        "creation": "2026-03-25T22:21:59.825Z",
        "lastAccessed": "2026-03-25T22:21:59.825Z"
    },
    {
        "key": "c_user",
        "value": "61578548880800",
        "domain": "facebook.com",
        "path": "/",
        "hostOnly": false,
        "creation": "2026-03-25T22:21:59.825Z",
        "lastAccessed": "2026-03-25T22:21:59.825Z"
    },
    {
        "key": "xs",
        "value": "24%3AWBZDsTp-fJcQzg%3A2%3A1774476432%3A-1%3A-1",
        "domain": "facebook.com",
        "path": "/",
        "hostOnly": false,
        "creation": "2026-03-25T22:21:59.825Z",
        "lastAccessed": "2026-03-25T22:21:59.825Z"
    },
    {
        "key": "fr",
        "value": "06CFbFN41hhrNmyqW.AWfsF5P0vbHlwfwDhpkuLMIOUFAn3dmxuWRHAKcTCgw9JEmogvY.BpxFx-..AAA.0.0.BpxFyX.AWcw-IGxG8VeLtY_52_gHngmP9A",
        "domain": "facebook.com",
        "path": "/",
        "hostOnly": false,
        "creation": "2026-03-25T22:21:59.825Z",
        "lastAccessed": "2026-03-25T22:21:59.825Z"
    },
    {
        "key": "locale",
        "value": "ne_NP",
        "domain": "facebook.com",
        "path": "/",
        "hostOnly": false,
        "creation": "2026-03-25T22:21:59.825Z",
        "lastAccessed": "2026-03-25T22:21:59.825Z"
    },
    {
        "key": "pas",
        "value": "61578548880800%3A2SPMbaKmf6",
        "domain": "facebook.com",
        "path": "/",
        "hostOnly": false,
        "creation": "2026-03-25T22:21:59.825Z",
        "lastAccessed": "2026-03-25T22:21:59.825Z"
    },
    {
        "key": "wl_cbv",
        "value": "v2%3Bclient_version%3A3122%3Btimestamp%3A1774476439",
        "domain": "facebook.com",
        "path": "/",
        "hostOnly": false,
        "creation": "2026-03-25T22:21:59.825Z",
        "lastAccessed": "2026-03-25T22:21:59.825Z"
    },
    {
        "key": "fbl_st",
        "value": "100626747%3BT%3A29574607",
        "domain": "facebook.com",
        "path": "/",
        "hostOnly": false,
        "creation": "2026-03-25T22:21:59.825Z",
        "lastAccessed": "2026-03-25T22:21:59.825Z"
    },
    {
        "key": "vpd",
        "value": "v1%3B800x424x2.294114351272583",
        "domain": "facebook.com",
        "path": "/",
        "hostOnly": false,
        "creation": "2026-03-25T22:21:59.825Z",
        "lastAccessed": "2026-03-25T22:21:59.825Z"
    }
]
